schemamodels/__init__.py
schemamodels/bases.py
schemamodels/dynamic.py
schemamodels/exceptions.py
schemamodels-0.9.1.dist-info/LICENSE
schemamodels-0.9.1.dist-info/LICENSES/CC0-1.0.txt
schemamodels-0.9.1.dist-info/LICENSES/GPL-3.0-or-later.txt
schemamodels-0.9.1.dist-info/METADATA
schemamodels-0.9.1.dist-info/WHEEL
schemamodels-0.9.1.dist-info/RECORD
