Metadata-Version: 2.1
Name: schemamodels
Version: 0.9.1
Summary: Dynamically create useful data classes from JSON schemas
License: GPL-3.0-or-later
Author: 'Jurnell Cockhren'
Author-email: jurnell@civichacker.com
Requires-Python: >=3.8,<4.0
Classifier: License :: OSI Approved :: GNU General Public License v3 or later (GPLv3+)
Classifier: Programming Language :: Python :: 3
Classifier: Programming Language :: Python :: 3.8
Classifier: Programming Language :: Python :: 3.9
Classifier: Programming Language :: Python :: 3.10
Classifier: Programming Language :: Python :: 3.11
Classifier: Programming Language :: Python :: 3.12
